app/routes/__init__.py
app/routes/health.py
app/routes/nlip.py
app/schemas/__init__.py
app/schemas/genai.py
app/schemas/nlip.py
app/server.py
app/utils/README.md
app/utils/__init__.py
app/utils/errors.py
app/utils/utils.py
nlip-0.1.0.dist-info/LICENSE
nlip-0.1.0.dist-info/METADATA
nlip-0.1.0.dist-info/WHEEL
nlip-0.1.0.dist-info/entry_points.txt
nlip-0.1.0.dist-info/RECORD
